typeracer_cheat/__init__.py
typeracer_cheat/command_line.py
typeracer_cheat/main.py
typeracer_cheat-0.0.2.dist-info/LICENSE
typeracer_cheat-0.0.2.dist-info/METADATA
typeracer_cheat-0.0.2.dist-info/WHEEL
typeracer_cheat-0.0.2.dist-info/entry_points.txt
typeracer_cheat-0.0.2.dist-info/top_level.txt
typeracer_cheat-0.0.2.dist-info/RECORD
