Metadata-Version: 2.1
Name: typeracer-cheat
Version: 0.0.2
Summary: A program that allows one to achieve extremely high speeds on typeracer.com on all game modes.
Home-page: https://github.com/RoastSea8/typeracer-cheat
Author: RoastSea8 (Aditya Tomar)
Author-email: aditya26042005@gmail.com
License: MIT
Keywords: typeracer,cheat,typeracercheat,typecheat,typefast,chromedriver,selenium,onlineraces
Platform: UNKNOWN
Classifier: Development Status :: 4 - Beta
Classifier: Topic :: Software Development :: Testing
Classifier: Topic :: System :: Installation/Setup
Classifier: Topic :: Software Development :: Libraries :: Python Modules
Classifier: License :: OSI Approved :: MIT License
Classifier: Programming Language :: Python :: 3
Classifier: Programming Language :: Python :: 3.6
Classifier: Programming Language :: Python :: 3.7
Classifier: Programming Language :: Python :: 3.8
Classifier: Programming Language :: Python :: 3.9
Classifier: Programming Language :: Python :: 3.10
Classifier: Operating System :: MacOS :: MacOS X
Classifier: Operating System :: Microsoft :: Windows
Requires-Python: >=3.6
License-File: LICENSE
Requires-Dist: selenium
Requires-Dist: chromedriver-autoinstall
